termstr/__init__.py
termstr/const.py
termstr/models.py
termstr/py.typed
termstr/utils.py
termstr-0.3.0.dist-info/METADATA
termstr-0.3.0.dist-info/WHEEL
termstr-0.3.0.dist-info/licenses/LICENSE
termstr-0.3.0.dist-info/RECORD
