Metadata-Version: 2.3
Name: termstr
Version: 0.3.0
Summary: `termstr` elevates terminal output with customizable color, style, and alignment options for text.
Project-URL: Issues, https://github.com/Lingxuan-Ye/termstr/issues
Project-URL: Source, https://github.com/Lingxuan-Ye/termstr
Author-email: Lingxuan Ye <love@lingxuan.io>
License-Expression: MIT
License-File: LICENSE
Classifier: Programming Language :: Python
Classifier: Programming Language :: Python :: 3.11
Classifier: Programming Language :: Python :: Implementation :: CPython
Requires-Python: >=3.11
